{
  "chat_id" : "${user_id}",
  "text" : "Привет! Я бот-помощник ДПСО \"Лиза Алерт\" 🚨. Я помогу тебе оставаться в курсе новых поисковых операций в твоем регионе",
  "parse_mode" : "markdown",
  "reply_markup" : {
    "resize_keyboard" : "true",
    "keyboard" : [
      [
        {
          "text" : "Получать уведомления 💬"
        }
      ],
      [
        {
          "text" : "Отписаться 🚫"
        }
      ]
    ]
  }
}